wolof/__init__.py
wolof/asr.py
wolof/model.py
wolof-0.0.3.dist-info/LICENSE
wolof-0.0.3.dist-info/METADATA
wolof-0.0.3.dist-info/WHEEL
wolof-0.0.3.dist-info/top_level.txt
wolof-0.0.3.dist-info/RECORD
