Metadata-Version: 2.1
Name: wolof
Version: 0.0.3
Summary: wolof is a python library for the Wolof language
Home-page: https://github.com/abdouaziz/wolof
Author: Abdou Aziz DIOP
Author-email: abdouaziz@gmail.com
License: UNKNOWN
Project-URL: Bug Tracker, https://github.com/abdouaziz/wolof/issues
Platform: UNKNOWN
Classifier: Programming Language :: Python :: 3
Classifier: License :: OSI Approved :: MIT License
Classifier: Operating System :: OS Independent
Requires-Python: >=3.6
License-File: LICENSE
